difotrain/__init__.py
difotrain/__main__.py
difotrain/learning/imitation.py
difotrain/representation/skeleton.py
difotrain/robot/controller.py
difotrain/simulation/pybullet_env.py
difotrain-0.1.1.dist-info/METADATA
difotrain-0.1.1.dist-info/WHEEL
difotrain-0.1.1.dist-info/entry_points.txt
difotrain-0.1.1.dist-info/licenses/LICENSE
difotrain-0.1.1.dist-info/RECORD
