Metadata-Version: 2.4
Name: difotrain
Version: 0.1.1
Summary: Human to Robot Motion Transfer
Author: Ashraf Galib Shaik
License: MIT License
License-File: LICENSE
Requires-Python: >=3.10
Requires-Dist: mediapipe
Requires-Dist: numpy
Requires-Dist: opencv-python
Requires-Dist: torch
